.DS_Store
demyst/.DS_Store
demyst/df/.DS_Store
demyst/df/__init__.py
demyst/df/command.py
demyst/df/df2.py
demyst/df/handler.py
demyst/df/utility.py
demyst/df/data/.DS_Store
demyst/df/data/v1/data-function.zip
demyst/df/data/v2/.DS_Store
demyst/df/data/v2/function/definition.py
demyst/df/data/v2/function/function.py
demyst/df/data/v2/function/requirements.txt
demyst_df-0.9.0.dist-info/METADATA
demyst_df-0.9.0.dist-info/WHEEL
demyst_df-0.9.0.dist-info/entry_points.txt
demyst_df-0.9.0.dist-info/top_level.txt
demyst_df-0.9.0.dist-info/RECORD
