Metadata-Version: 2.1
Name: demyst-df
Version: 0.9.0
Author: Demyst Data
Author-email: info@demystdata.com
Requires-Dist: demyst-common (>=0.9.0)
Requires-Dist: click
Requires-Dist: boto3
Requires-Dist: botocore
Requires-Dist: tabulate
Requires-Dist: halo
Requires-Dist: glom
